AUTHORS
LICENSE
MANIFEST.in
README
setup.py
bookmarks/__init__.py
bookmarks/admin.py
bookmarks/forms.py
bookmarks/models.py
bookmarks/search_indexes.py
bookmarks/urls.py
bookmarks/views.py
bookmarks/fixtures/bookmarks.json
bookmarks/migrations/0001_initial.py
bookmarks/migrations/0002_auto_20160301_1154.py
bookmarks/migrations/__init__.py
bookmarks/templates/bookmarks/tags.html
bookmarks/templatetags/__init__.py
bookmarks/templatetags/bookmark_tags.py
bookmarks/tests/__init__.py
bookmarks/tests/factories.py
bookmarks/tests/test_forms.py
bookmarks/tests/test_legacy.py
bookmarks/tests/test_models.py
incuna_bookmarks.egg-info/PKG-INFO
incuna_bookmarks.egg-info/SOURCES.txt
incuna_bookmarks.egg-info/dependency_links.txt
incuna_bookmarks.egg-info/top_level.txt